{
  "kind": "collectionType",
  "collectionName": "products",
  "info": {
    "name": "Products",
    "description": ""
  },
  "options": {
    "increments": true,
    "timestamps": true,
    "draftAndPublish": true
  },
  "pluginOptions": {},
  "attributes": {
    "title": {
      "type": "string"
    },
    "description": {
      "type": "string"
    },
    "image": {
      "model": "file",
      "via": "related",
      "allowedTypes": [
        "images",
        "files",
        "videos"
      ],
      "plugin": "upload",
      "required": false,
      "pluginOptions": {}
    },
    "price": {
      "type": "decimal"
    },
    "featured": {
      "type": "boolean"
    }
  }
}
